kafka_framework/__init__.py
kafka_framework/app.py
kafka_framework/dependencies/__init__.py
kafka_framework/dependencies/injection.py
kafka_framework/exceptions/__init__.py
kafka_framework/exceptions/handlers.py
kafka_framework/kafka/__init__.py
kafka_framework/kafka/consumer.py
kafka_framework/kafka/producer.py
kafka_framework/middleware/__init__.py
kafka_framework/middleware/base.py
kafka_framework/middleware/logger_middleware.py
kafka_framework/models/__init__.py
kafka_framework/models/config.py
kafka_framework/models/message.py
kafka_framework/routing/__init__.py
kafka_framework/routing/router.py
kafka_framework/serialization/__init__.py
kafka_framework/serialization/avro.py
kafka_framework/serialization/base.py
kafka_framework/serialization/json.py
kafka_framework/serialization/protobuf.py
kafka_framework/utils/__init__.py
kafka_framework/utils/dlq.py
kafka_framework/utils/logging.py
kafka_framework-0.1.4.dist-info/METADATA
kafka_framework-0.1.4.dist-info/WHEEL
kafka_framework-0.1.4.dist-info/RECORD
