Metadata-Version: 2.4
Name: kafka-framework
Version: 0.1.4
Summary: A FastAPI-style Python framework for Kafka-based applications
Project-URL: Homepage, https://github.com/ahdhani/kafka-framework
Project-URL: Repository, https://github.com/ahdhani/kafka-framework
Project-URL: Issues, https://github.com/ahdhani/kafka-framework/issues
Author-email: Ahammad Hani <ahmedhanitk@gmail.com>
License: MIT
Requires-Python: >=3.10
Requires-Dist: aiokafka>=0.12.0
Provides-Extra: all
Requires-Dist: fastavro>=1.8.0; extra == 'all'
Requires-Dist: protobuf>=4.23.3; extra == 'all'
Provides-Extra: avro
Requires-Dist: fastavro>=1.8.0; extra == 'avro'
Provides-Extra: protobuf
Requires-Dist: protobuf>=4.23.3; extra == 'protobuf'
